LICENSE.txt
MANIFEST.in
README.rst
setup.py
gengo/__init__.py
gengo/_version.py
gengo/gengo.py
gengo/mockdb.py
gengo.egg-info/PKG-INFO
gengo.egg-info/SOURCES.txt
gengo.egg-info/dependency_links.txt
gengo.egg-info/requires.txt
gengo.egg-info/top_level.txt