Metadata-Version: 1.1
Name: gengo
Version: 0.1.31
Summary: Official Python library for interfacing with the Gengo API.
Home-page: https://github.com/gengo/gengo-python
Author: Gengo
Author-email: api@gengo.com
License: New BSD License
Keywords: gengo translation language api
Platform: UNKNOWN
Classifier: Development Status :: 5 - Production/Stable
Classifier: Intended Audience :: Developers
Classifier: License :: OSI Approved :: BSD License
Classifier: Topic :: Software Development :: Libraries :: Python Modules
Classifier: Topic :: Internet
Classifier: Programming Language :: Python :: 2.7
Classifier: Programming Language :: Python :: 3
Classifier: Programming Language :: Python :: 3.2
Classifier: Programming Language :: Python :: 3.3
Classifier: Programming Language :: Python :: 3.4
